alfred/__init__.py
alfred/action.py
alfred/agent_for_shell.py
alfred/main.py
process_manager/__init__.py
process_manager/action.py
process_manager/agent.py
ceo_alfred-0.0.11b0.dist-info/LICENSE
ceo_alfred-0.0.11b0.dist-info/METADATA
ceo_alfred-0.0.11b0.dist-info/WHEEL
ceo_alfred-0.0.11b0.dist-info/entry_points.txt
ceo_alfred-0.0.11b0.dist-info/top_level.txt
ceo_alfred-0.0.11b0.dist-info/RECORD
