Metadata-Version: 2.1
Name: ceo-alfred
Version: 0.0.11b0
Summary: Alfred is an assistant in your shell.
Home-page: https://github.com/vortezwohl/CEO-Alfred-TheProcessManager
Author: vortezwohl
Author-email: vortez.wohl@gmail.com
License: GNU GENERAL PUBLIC LICENSE
Project-URL: Bug Tracker, https://github.com/vortezwohl/CEO-Alfred-TheProcessManager/issues
Classifier: Programming Language :: Python :: 3
Classifier: Operating System :: OS Independent
Classifier: Natural Language :: English
Requires-Python: >=3.10
License-File: LICENSE
Requires-Dist: psutil >=6.1.0
Requires-Dist: ceo-py >=0.6.0rc0
Requires-Dist: python-dotenv >=1.0.1
Requires-Dist: sympy >=1.13.3
Requires-Dist: colorama >=0.4.6
